mapdepot/__init__.py
mapdepot/cli.py
mapdepot/schemas/__init__.py
mapdepot/schemas/base.py
mapdepot/schemas/topographic.py
mapdepot-0.1.2.dist-info/DESCRIPTION.rst
mapdepot-0.1.2.dist-info/METADATA
mapdepot-0.1.2.dist-info/RECORD
mapdepot-0.1.2.dist-info/WHEEL
mapdepot-0.1.2.dist-info/entry_points.txt
mapdepot-0.1.2.dist-info/metadata.json
mapdepot-0.1.2.dist-info/top_level.txt
