Metadata-Version: 2.0
Name: mapdepot
Version: 0.1.2
Summary: Map Depot's helpful scripts for indexing their data.
Home-page: UNKNOWN
Author: UNKNOWN
Author-email: UNKNOWN
License: UNKNOWN
Platform: UNKNOWN
Requires-Dist: click
